_boot.py
_onewire.pyi
_thread.pyi
_uasyncio.pyi
apa106.pyi
array.pyi
binascii.pyi
btree.pyi
cmath.pyi
dht.pyi
dotstar.py
ds18x20.pyi
errno.pyi
esp.pyi
esp32.pyi
flashbdev.pyi
framebuf.pyi
gc.pyi
hashlib.pyi
heapq.pyi
inisetup.pyi
io.pyi
json.pyi
machine.pyi
math.pyi
micropython.pyi
micropython_.pyi
neopixel.pyi
network.pyi
ntptime.pyi
onewire.pyi
os.pyi
platform.pyi
random.pyi
select.pyi
socket.pyi
ssl.pyi
struct.pyi
sys.pyi
time.pyi
tinypico.py
uarray.pyi
uasyncio/__init__.pyi
uasyncio/core.pyi
uasyncio/event.pyi
uasyncio/funcs.pyi
uasyncio/lock.pyi
uasyncio/stream.pyi
uasyncio/task.py
ubinascii.pyi
ubluetooth.pyi
ucollections.pyi
ucryptolib.pyi
uctypes.pyi
uerrno.pyi
uhashlib.pyi
uheapq.pyi
uio.pyi
ujson.pyi
umachine.pyi
umqtt/__init__.pyi
umqtt/robust.pyi
umqtt/simple.pyi
uos.pyi
upip.py
upip_utarfile.py
uplatform.pyi
urandom.pyi
ure.pyi
urequests.pyi
uselect.pyi
usocket.pyi
ussl.pyi
ustruct.pyi
usys.pyi
utime.pyi
utimeq.pyi
uwebsocket.pyi
uzlib.pyi
webrepl.py
webrepl_setup.py
websocket.pyi
websocket_helper.pyi
zlib.pyi
micropython_esp32_um_tinypico_stubs-1.19.1.post7.dist-info/LICENSE.md
micropython_esp32_um_tinypico_stubs-1.19.1.post7.dist-info/METADATA
micropython_esp32_um_tinypico_stubs-1.19.1.post7.dist-info/WHEEL
micropython_esp32_um_tinypico_stubs-1.19.1.post7.dist-info/RECORD
